AUTHORS
LICENSE
MANIFEST.in
README.rst
setup.cfg
setup.py
src/anycrypt/__init__.py
src/anycrypt/main.py
src/anycrypt.egg-info/PKG-INFO
src/anycrypt.egg-info/SOURCES.txt
src/anycrypt.egg-info/dependency_links.txt
src/anycrypt.egg-info/entry_points.txt
src/anycrypt.egg-info/top_level.txt