Metadata-Version: 1.2
Name: anycrypt
Version: 0.0.1a1
Summary: anycrypt is an information encryption and decryption utility.
Home-page: http://www.codetrax.org/projects/anycrypt
Author: George Notaras
Author-email: gnot@g-loaded.eu
Maintainer: George Notaras
Maintainer-email: gnot@g-loaded.eu
License: GPLv2+
Download-URL: https://source.codetrax.org/anycrypt
Platform: any
Classifier: Development Status :: 3 - Alpha
Classifier: Environment :: Console
Classifier: Intended Audience :: System Administrators
Classifier: License :: OSI Approved :: GNU General Public License v2 or later (GPLv2+)
Classifier: Natural Language :: English
Classifier: Operating System :: OS Independent
Classifier: Programming Language :: Python
Classifier: Topic :: System
